NetCalculate/NetCalculate.py
NetCalculate/__init__.py
NetCalculate-0.0.2.dist-info/LICENSE
NetCalculate-0.0.2.dist-info/METADATA
NetCalculate-0.0.2.dist-info/WHEEL
NetCalculate-0.0.2.dist-info/top_level.txt
NetCalculate-0.0.2.dist-info/RECORD
